dm_robotics/manipulation/__init__.py
dm_robotics/manipulation/run_tests.py
dm_robotics/manipulation/props/mesh_object.py
dm_robotics/manipulation/props/mesh_object_test.py
dm_robotics/manipulation/props/object_collection.py
dm_robotics/manipulation/props/parametric_object/parametric_object.py
dm_robotics/manipulation/props/parametric_object/parametric_object_test.py
dm_robotics/manipulation/props/parametric_object/rgb_objects/parametric_rgb_object.py
dm_robotics/manipulation/props/parametric_object/rgb_objects/parametric_rgb_object_test.py
dm_robotics/manipulation/props/parametric_object/rgb_objects/rgb_object_names.py
dm_robotics/manipulation/props/rgb_objects/rgb_object.py
dm_robotics/manipulation/props/rgb_objects/rgb_object_test.py
dm_robotics/manipulation/props/rgb_objects/assets/rgb_v1.3/meshes/heldout/e2_sds5_shr0_drf0_hlw0_shx0_shy0_scx49_scy49_scz50.stl
dm_robotics/manipulation/props/rgb_objects/assets/rgb_v1.3/meshes/heldout/e3_sds4_shr20_drf0_hlw0_shx0_shy0_scx48_scy50_scz55.stl
dm_robotics/manipulation/props/rgb_objects/assets/rgb_v1.3/meshes/heldout/e5_sds4_shr0_drf0_hlw0_shx0_shy11_scx50_scy50_scz50.stl
dm_robotics/manipulation/props/rgb_objects/assets/rgb_v1.3/meshes/heldout/e6_sds4_shr0_drf0_hlw0_shx0_shy0_scx45_scy45_scz77.stl
dm_robotics/manipulation/props/rgb_objects/assets/rgb_v1.3/meshes/heldout/f2_sds5_shr0_drf0_hlw0_shx0_shy0_scx50_scy50_scz50.stl
dm_robotics/manipulation/props/rgb_objects/assets/rgb_v1.3/meshes/heldout/f3_sds4_shr13_drf0_hlw0_shx0_shy0_scx49_scy50_scz53.stl
dm_robotics/manipulation/props/rgb_objects/assets/rgb_v1.3/meshes/heldout/f5_sds4_shr0_drf0_hlw0_shx0_shy7_scx50_scy50_scz50.stl
dm_robotics/manipulation/props/rgb_objects/assets/rgb_v1.3/meshes/heldout/f6_sds4_shr0_drf0_hlw0_shx0_shy0_scx47_scy47_scz68.stl
dm_robotics/manipulation/props/rgb_objects/assets/rgb_v1.3/meshes/heldout/h2_sds6_shr0_drf0_hlw0_shx0_shy0_scx48_scy48_scz50.stl
dm_robotics_manipulation-0.10.0.dist-info/METADATA
dm_robotics_manipulation-0.10.0.dist-info/WHEEL
dm_robotics_manipulation-0.10.0.dist-info/top_level.txt
dm_robotics_manipulation-0.10.0.dist-info/zip-safe
dm_robotics_manipulation-0.10.0.dist-info/RECORD
