Metadata-Version: 2.4
Name: dm_robotics-manipulation
Version: 0.10.0
Summary: Parametrically defined mesh objects
Home-page: https://github.com/deepmind/dm_robotics/tree/main/py/manipulation
Author: DeepMind
License: Apache 2.0
Classifier: Development Status :: 5 - Production/Stable
Classifier: Programming Language :: Python :: 3
Classifier: License :: OSI Approved :: Apache Software License
Classifier: Operating System :: OS Independent
Classifier: Topic :: Software Development :: Libraries
Classifier: Topic :: Scientific/Engineering
Requires-Python: >=3.9, <3.13
Requires-Dist: dm_robotics-transformations
Requires-Dist: dm_robotics-geometry
Requires-Dist: dm_robotics-agentflow
Requires-Dist: dm_robotics-controllers
Requires-Dist: dm_robotics-moma
Requires-Dist: absl-py>=0.9.0
Requires-Dist: numpy<3.0,>=2.0
Requires-Dist: typing-extensions>=3.7.4
Requires-Dist: dm_control==1.0.31
Requires-Dist: mujoco==3.3.3
Dynamic: author
Dynamic: classifier
Dynamic: description
Dynamic: description-content-type
Dynamic: home-page
Dynamic: license
Dynamic: requires-dist
Dynamic: requires-python
Dynamic: summary
